LICENSE.md
MANIFEST.in
README.md
requirements.txt
setup.py
alice_bus_client/__init__.py
alice_bus_client/conf.py
alice_bus_client/message.py
alice_bus_client/send_func.py
alice_bus_client/client/__init__.py
alice_bus_client/client/client.py
alice_bus_client/client/collector.py
alice_bus_client/client/waiter.py
alice_bus_client/util/__init__.py
alice_bus_client/util/scheduler.py
alice_bus_client/util/utils.py
alice_messagebus_client.egg-info/PKG-INFO
alice_messagebus_client.egg-info/SOURCES.txt
alice_messagebus_client.egg-info/dependency_links.txt
alice_messagebus_client.egg-info/requires.txt
alice_messagebus_client.egg-info/top_level.txt
test/test.conf
test/test_client.py
test/test_conf.py
test/test_message.py